{
    "config": {
        "run": "vqe-bigT-simulation",
        "bigT": [
            10,
            20,
            30,
            40,
            50
        ],
        "nqubits": 5,
        "state": "dmatrix",
        "output": {
            "file_name_prefix": "vqe-time-rel-noise-experement_5Q",
            "draw": {
                "status": true,
                "fig_dpi": 100,
                "type": "png"
            }
        },
        "observable": {
            "def": "ising",
            "coefficients": {
                "cn": [
                    0.5,
                    0.5,
                    0.5,
                    0.5
                ],
                "bn": [
                    1.0,
                    1.0,
                    1.0,
                    1.0,
                    1.0
                ],
                "r": 1
            }
        },
        "ansatz": {
            "layer": 30,
            "gateset": 1,
            "ugate": {
                "type": "heisenberg",
                "coefficients": {
                    "cn": [
                        0.5,
                        0.5,
                        0.5,
                        0.5
                    ],
                    "bn": [
                        1.0,
                        1.0,
                        1.0,
                        1.0,
                        1.0
                    ],
                    "r": 0
                },
                "time": {
                    "min": 0.0,
                    "max": 20
                }
            }
        },
        "vqe": {
            "iteration": 10,
            "optimization": {
                "status": true,
                "algorithm": "SLSQP",
                "constraint": true
            }
        },
        "init_param": {
            "value": "random"
        },
        "noise_profile": {
            "status": false,
            "type": "dephasing",
            "noise_prob": [
                0.001,
                0.001,
                0.0,
                0.0
            ],
            "noise_on_init_param": {
                "status": false,
                "value": 0
            }
        },
        "redundant": {
            "identity_factors": [
                [
                    0,
                    0,
                    0,
                    0
                ],
                [
                    1,
                    1,
                    1,
                    1
                ]
            ]
        },
        "zne": {
            "method": "richardson",
            "degree": 1,
            "sampling": "default",
            "data_points": null
        }
    },
    "output": {
        "exact_sol": -6.026674183332271,
        "initial_cost_history": [
            4.075960981095176,
            3.8873808671436296,
            3.845805077917014,
            3.8458432314894178,
            3.953337969323737,
            3.8050177786617274,
            3.6221634422407787,
            3.705858781991151,
            4.039021505953222,
            4.227223935444699
        ],
        "initial_randm_param_values": [
            {
                "time": [
                    0.032624531200122764,
                    0.5945083661472772,
                    0.8069202354229565,
                    1.8849087362628625,
                    2.500880531720766,
                    4.3472542863602115,
                    4.772478516938445,
                    4.979956616716954,
                    5.472662189238216,
                    7.534854785219252,
                    8.28941892819831,
                    8.443446414636552,
                    8.801078996044422,
                    8.845799318708117,
                    11.346982489492824,
                    11.95086832945371,
                    12.476876876779137,
                    12.846104140488494,
                    13.172255737542027,
                    13.245006755560382,
                    13.415287459320028,
                    13.521573012608544,
                    14.402884476444296,
                    14.445999331145746,
                    16.70101545347555,
                    17.33080499742084,
                    18.053099681911135,
                    18.10254456236821,
                    19.070870920002182,
                    19.180066011384863
                ],
                "theta": [
                    0.015737187474044546,
                    0.020050424540276137,
                    0.05627715521365918,
                    0.037661442240038534,
                    0.07313057461819415,
                    0.0533063835242816,
                    0.009531588888154176,
                    0.0926584873955069,
                    0.08858951773865661,
                    0.07425458853723844,
                    0.03724934723223864,
                    0.006098372049318502,
                    0.08870769569780576,
                    0.036334092435194434,
                    0.059706798349149916,
                    0.026123681825627423,
                    0.08488239263609586,
                    0.07277222555377434,
                    0.03932121713546893,
                    0.01451615005796827,
                    0.06156989946195435,
                    0.09686403758933815,
                    0.09744513913634495,
                    0.07597662322874954,
                    0.03282523750170496,
                    0.0637914855448538,
                    0.07442484982624302,
                    0.005701995253779235,
                    0.003583621109611912,
                    0.062028151563583225,
                    0.018928970950345105,
                    0.03228081523543482,
                    0.027450541332029166,
                    0.047511067990954836,
                    0.07669601490146788,
                    0.002479012485152732,
                    0.045869498236639265,
                    0.09351744372397434,
                    0.005834036734934412,
                    0.039335676685514825,
                    0.035699283568498406,
                    0.023080581850045925,
                    0.019220821683766987,
                    0.02886820561803487,
                    0.018171229235551534,
                    0.06106832463917736,
                    0.03401646603376076,
                    0.07894475357266245,
                    0.05977906844594221,
                    0.01991061954590754,
                    0.02581801857388587,
                    0.0035296960915543463,
                    0.0005240446371197028,
                    0.09036900354977506,
                    0.003932089462239785,
                    0.08495397141565574,
                    0.06965036475208825,
                    0.05369033070845519,
                    0.0415003475690898,
                    0.06645928238216513
                ]
            },
            {
                "time": [
                    0.6993009239396697,
                    1.3657555310862723,
                    1.5782985911899439,
                    2.5742312995233263,
                    4.169376138413776,
                    4.856314162812103,
                    5.333647731199496,
                    5.747853320983937,
                    6.598984575413005,
                    7.187165347851026,
                    8.938262843257075,
                    10.256200283580823,
                    10.375624398040436,
                    12.831736232549195,
                    13.25936890948209,
                    13.500619297485649,
                    13.84522843648936,
                    14.186746294777118,
                    14.385412601797828,
                    14.44073829919364,
                    14.90671324300639,
                    15.52881328500239,
                    15.667176579640223,
                    16.016329410361106,
                    16.465469556765925,
                    17.068977596751516,
                    17.74380054331546,
                    17.88416597375876,
                    19.465424944567754,
                    19.517545756828248
                ],
                "theta": [
                    0.09279144076293018,
                    0.02178351955348592,
                    0.04496361037559771,
                    0.045460351221296096,
                    0.04685822957622341,
                    0.012779290270936073,
                    0.05171453231264814,
                    0.01676228394126633,
                    0.08747982791012616,
                    0.045882767096845994,
                    0.054315963966070684,
                    0.021714841727711556,
                    0.039705168066020084,
                    0.07610868524130153,
                    0.033987461785077035,
                    0.00817452390733593,
                    0.08172601025711851,
                    0.07057495500945685,
                    0.0673639154819131,
                    0.0820439407580903,
                    0.058370760743573814,
                    0.09342562396642366,
                    0.07051014869773493,
                    0.09139559801162205,
                    0.05094573523127708,
                    0.007857318278722625,
                    0.04686232253121428,
                    0.025550454717369275,
                    0.0552243791383376,
                    0.08052552159871074,
                    0.08900351975073828,
                    0.08979407136557165,
                    0.05076494255931707,
                    0.028225498309250887,
                    0.07842410885837599,
                    0.048888945173933746,
                    0.052732299837556486,
                    0.07028207174912891,
                    0.09291066064257775,
                    0.08266040265363356,
                    0.06484759051544246,
                    0.08389823512242234,
                    0.03261017921908498,
                    0.08786832377138842,
                    0.07321857925068002,
                    0.02727408743397665,
                    0.03397496559039315,
                    0.02038777933294358,
                    0.07760268006584398,
                    0.01335348147883988,
                    0.024195723638119216,
                    0.08164219300746972,
                    0.05179108841901266,
                    0.026903385097521926,
                    0.001614502345688218,
                    0.03789773458856038,
                    0.03210895673105925,
                    0.016783396763461345,
                    0.00960125793118849,
                    0.04175654022463731
                ]
            },
            {
                "time": [
                    0.18736499588055677,
                    0.9116986481610345,
                    0.9611656463598139,
                    1.5003036067236697,
                    1.8569716566620498,
                    2.184359645135192,
                    2.2450205702981996,
                    2.9706736028609515,
                    3.1199015509774553,
                    3.873009686008897,
                    4.027188740517717,
                    4.201378471139265,
                    4.217967308484325,
                    5.210921725069781,
                    6.05027417650557,
                    6.263914830715778,
                    7.3016382877991814,
                    8.036696034046123,
                    8.457177021281069,
                    10.237588209570047,
                    10.308395925881207,
                    12.264223201421224,
                    13.425266520472917,
                    13.653384031606858,
                    14.316566390738894,
                    17.725715682889764,
                    18.18147145359412,
                    18.45419675517779,
                    18.842749783652398,
                    19.699808226484713
                ],
                "theta": [
                    0.04536809831233838,
                    0.058290221401704395,
                    0.0818154930325707,
                    0.012255193692320733,
                    0.010539319594669583,
                    0.06359192963585432,
                    0.07306443648167991,
                    0.002909271453374518,
                    0.033564429225327284,
                    0.020971908918926654,
                    0.07185578912290276,
                    0.05504678770675006,
                    0.08295463587903945,
                    0.024886325221383055,
                    0.04134749719880357,
                    0.037763838092627726,
                    0.06255639888612002,
                    0.03383545502264358,
                    0.07047779508408145,
                    0.056714802165365175,
                    0.08821835571437699,
                    0.06999327182637996,
                    0.04451719973648369,
                    0.028796949172564746,
                    0.03850613661580023,
                    0.05169300354406257,
                    0.06555248951664785,
                    0.08133238332937959,
                    0.045262534664055415,
                    0.05364211759129392,
                    0.0043359994709798125,
                    0.06091850069352314,
                    0.023836393917272037,
                    0.01970288734189333,
                    0.01962599542992918,
                    0.09206116416701524,
                    0.07715708585378728,
                    0.01067888936398549,
                    0.0850606519705272,
                    0.023739479843324907,
                    0.00791465823452785,
                    0.041617414196070505,
                    0.04718385339253383,
                    0.07145133164604596,
                    0.004810666348221748,
                    0.09672217976751504,
                    0.08459348003476613,
                    0.05274873241048783,
                    0.03999633559220294,
                    0.08719238142936209,
                    0.06405098022473665,
                    0.0729438600442318,
                    0.0331177687520296,
                    0.05273349154034251,
                    0.07625173108245788,
                    0.018787711930240137,
                    0.0772074053559109,
                    0.04928479020812696,
                    0.05381022043486081,
                    0.04014671941232992
                ]
            },
            {
                "time": [
                    0.4148708922117095,
                    1.084451017992143,
                    1.3889390800647572,
                    1.5283037523684295,
                    1.9093248756991277,
                    2.5609387360503932,
                    2.7390316730789332,
                    2.930881186947929,
                    3.1266247506822475,
                    3.4183312489642526,
                    3.9692892277435443,
                    4.402553308897104,
                    4.8020505423262305,
                    5.297539676492622,
                    6.16424423415827,
                    6.807269497422244,
                    7.61552007931477,
                    9.89687364433787,
                    10.832971206258712,
                    11.192473420490705,
                    11.354447764086302,
                    12.709846377775907,
                    13.451335506379714,
                    15.285060546394236,
                    15.345128489773812,
                    15.714438611839006,
                    17.12835085776964,
                    17.758275081140514,
                    17.931799834078927,
                    18.916491391127657
                ],
                "theta": [
                    0.033328956252307675,
                    0.08192233931255044,
                    0.029674134198446125,
                    0.023309715938549958,
                    0.007164010492276662,
                    0.04246706402955757,
                    0.03152257447637046,
                    0.006572821264443285,
                    0.0689716024687023,
                    0.09408368954361067,
                    0.01662148306927259,
                    0.04000451990763248,
                    0.02541736007772735,
                    0.054973794391352616,
                    0.03995281649024982,
                    0.04249252844903198,
                    0.030050850831405285,
                    0.06195107146860283,
                    0.04089107608076489,
                    0.08259895071019338,
                    0.08091993480325432,
                    0.07682828361546579,
                    0.025821231198776273,
                    0.07182380078589114,
                    0.08096568597578764,
                    0.013577204140502053,
                    0.06948839206981416,
                    0.0604885824782122,
                    0.08402552222746422,
                    0.00913392083720015,
                    0.08125481762403332,
                    0.061161359287687116,
                    0.08747793563553086,
                    0.09252629495798674,
                    0.021561210656470486,
                    0.0012938215191990122,
                    0.02669167064549212,
                    0.07186289485935314,
                    0.00014030562677741498,
                    0.04768405123313835,
                    0.08805325343221902,
                    0.02523664492628146,
                    0.002356990003804549,
                    0.08150599398236891,
                    0.024220315710618303,
                    0.06914633128471206,
                    0.011217146664346478,
                    0.08361897007646708,
                    0.0920935597614016,
                    0.020901315243027543,
                    0.09403622692386515,
                    0.07536549369599005,
                    0.09216864843280888,
                    0.06625248269136096,
                    0.058610593439793024,
                    0.034207250102302536,
                    0.06695525358547608,
                    0.06938504817192796,
                    0.06561480457139121,
                    0.04469540726160305
                ]
            },
            {
                "time": [
                    0.08673670397288946,
                    0.3888879001750256,
                    1.070364049288588,
                    1.6042804480850514,
                    1.639235528663756,
                    2.827793993012966,
                    5.320216200701737,
                    5.934042129445785,
                    6.628174860841314,
                    7.244095063622664,
                    8.1853640191164,
                    8.306808036734664,
                    9.088624208384413,
                    9.277097186179537,
                    10.195050544501488,
                    11.836722199777629,
                    11.979087373828527,
                    12.329087416760121,
                    12.647237936594324,
                    13.137125628903693,
                    14.066745013808754,
                    14.670662906340365,
                    15.331683195641048,
                    17.098831848540048,
                    17.62791538886085,
                    17.651676295471518,
                    17.85243028635365,
                    18.231949296171518,
                    18.520641835784023,
                    18.528936667301707
                ],
                "theta": [
                    0.04979564729306575,
                    0.028497483008360937,
                    0.09877252125140899,
                    0.02795041240194406,
                    0.05340146983049859,
                    0.02297722853660853,
                    0.051093819021493715,
                    0.03713224821957674,
                    0.058140105092427785,
                    0.09127248330910528,
                    0.09134235859365875,
                    0.07462681040017513,
                    0.02157537666570879,
                    0.07236109138307008,
                    0.047740816320031056,
                    0.005109852723137343,
                    0.08138876701029057,
                    0.07973720919954536,
                    0.03820861051626783,
                    0.09077172051087785,
                    0.009091435526908932,
                    0.002899001387741129,
                    0.0008358868554119159,
                    0.09873112318529881,
                    0.008448896563221564,
                    0.03354083561156505,
                    0.09804356507860766,
                    0.014776003172990848,
                    0.07801864592786062,
                    0.08119760688755809,
                    0.07190112871036985,
                    0.051420697362980196,
                    0.0009742882106290375,
                    0.0553996400504752,
                    0.07473795389745222,
                    0.09434667213597665,
                    0.02241121653871694,
                    0.031830353092890416,
                    0.038605293885404394,
                    0.03897937209102919,
                    0.06289264892531732,
                    0.04272839304268419,
                    0.05950543757185964,
                    0.034076175449697155,
                    0.05731159264226622,
                    0.04201120445371681,
                    0.0723274806450194,
                    0.09862574906273915,
                    0.051994428452241594,
                    0.028951872038154837,
                    0.05284989305278644,
                    0.011511674764739977,
                    0.031480325734165836,
                    0.037634790120472675,
                    0.0905577703496969,
                    0.029171444695377337,
                    0.01137650742606956,
                    0.0738238870518874,
                    0.032037174403891526,
                    0.07098216238512765
                ]
            },
            {
                "time": [
                    0.07296901376894871,
                    0.7865207244940842,
                    2.6195983910376497,
                    3.6067181336750265,
                    3.6389533516376016,
                    4.232758439353557,
                    4.606842088107217,
                    5.276798320317619,
                    5.3150288882528525,
                    5.374006310285056,
                    5.618211643736197,
                    5.840396717242699,
                    6.265785020349703,
                    9.447838788452223,
                    10.052089951008607,
                    10.226832655579958,
                    10.984841952771038,
                    11.001207866051422,
                    12.573943143963572,
                    13.86956084185061,
                    15.214084192313717,
                    15.775774186111171,
                    16.543087929931204,
                    16.76351783034442,
                    16.996403468454794,
                    17.636930816898317,
                    18.33646876311701,
                    18.63170941673811,
                    19.342379265531868,
                    19.896944466978216
                ],
                "theta": [
                    0.052977092523075336,
                    0.03486753838382158,
                    0.0542348376759245,
                    0.01283025304171296,
                    0.02428960431490548,
                    0.09265830243047353,
                    0.052849612388803785,
                    0.03791979194975096,
                    0.016425836192560852,
                    0.013917007513916047,
                    0.0629496032067618,
                    0.07319901986769577,
                    0.031468281570474564,
                    0.09911458848530305,
                    0.07835897675115021,
                    0.011244923064967228,
                    0.011270862097367352,
                    0.006032816743621894,
                    0.013403866819219968,
                    0.03635689368216614,
                    0.03934228115657512,
                    0.08469297155630968,
                    0.02476203855580237,
                    0.01123911862492788,
                    0.03165674467034596,
                    0.06920711711792514,
                    0.07845878052601594,
                    0.0917509528047275,
                    0.0021234391758504834,
                    0.015166226556847096,
                    0.09743194883697257,
                    0.03470924277070494,
                    0.04481112773576932,
                    0.021756270895092713,
                    0.05609249079313105,
                    0.08799160033661915,
                    0.0921368673032778,
                    0.031683319561862065,
                    0.08477856106968128,
                    0.08512599755045208,
                    0.06132110663805947,
                    0.08039937232314745,
                    0.05809415060195714,
                    0.09377486346051908,
                    0.04068940219605424,
                    0.04391796159100784,
                    0.017908712636403968,
                    0.06453554244284104,
                    0.034138487545006556,
                    0.08336676650025034,
                    0.026114203659572212,
                    0.08674409708197976,
                    0.0984148469539217,
                    0.06787145263056044,
                    0.07794966582162687,
                    0.04689514438052758,
                    0.06931613222207215,
                    0.008868044231078221,
                    0.05347094155066373,
                    0.07768984571627603
                ]
            },
            {
                "time": [
                    0.14676459022620714,
                    0.5541015255579906,
                    1.1565489420088881,
                    1.2529146414242587,
                    2.9774305451519756,
                    3.1387400289318013,
                    3.508376232219619,
                    5.250356547517974,
                    5.670990572315542,
                    5.6711131203246445,
                    6.189650398297335,
                    6.637280749055911,
                    7.336674217484196,
                    7.62489309518398,
                    7.700829321955583,
                    8.992594684882562,
                    10.289975713008097,
                    13.602418445813944,
                    14.004553180267756,
                    15.284467346965744,
                    15.377782269335079,
                    15.88840387113466,
                    16.353324905317066,
                    17.070419392671536,
                    17.661579966793497,
                    17.702976052798377,
                    18.151151000666516,
                    18.152086815833123,
                    19.795172147433497,
                    19.82546616735125
                ],
                "theta": [
                    0.07482940222397547,
                    0.0026932985366360574,
                    0.03750082647615565,
                    0.07531872496537446,
                    0.09286324616947363,
                    0.07362333628479105,
                    0.05729161548190334,
                    0.07918681545815592,
                    0.036769529971868053,
                    0.0690536590481268,
                    0.06980931277826974,
                    0.014033542955251067,
                    0.07853291885399655,
                    0.02259756068138811,
                    0.05243533082637725,
                    0.09075130316466412,
                    0.004562264071458999,
                    0.09986407316343067,
                    0.09018247133972469,
                    0.09142640206279372,
                    0.0931601599586515,
                    0.04744968527808986,
                    0.03588914682741928,
                    0.012631216217019126,
                    0.0896672736900856,
                    0.07216085275277634,
                    0.08902848791344958,
                    0.09233829961075649,
                    0.09547159283679017,
                    0.018912493108145124,
                    0.0943667919965069,
                    0.039356113405363116,
                    0.019441349082998917,
                    0.006296283436269524,
                    0.06780143402534182,
                    0.0966859393292971,
                    0.07204020036002738,
                    0.0017693897678378923,
                    0.0202619987895039,
                    0.08955919696619193,
                    0.006921424004806509,
                    0.012732282699606091,
                    0.004251839937424173,
                    0.052391295537431375,
                    0.029269619747887735,
                    0.06376118452854034,
                    0.0827544787026468,
                    0.020922789539918565,
                    0.023866878190829333,
                    0.09513018633644886,
                    0.04094457349149292,
                    0.036811675317597124,
                    0.09886349361298327,
                    0.06274263003522744,
                    0.056598183704471464,
                    0.08965745236782131,
                    0.07303814923995096,
                    0.003300388595320525,
                    0.06511501196798719,
                    0.09029033908596124
                ]
            },
            {
                "time": [
                    0.5108111035177565,
                    0.7170080369274845,
                    0.7653437169619082,
                    1.3744325610732955,
                    2.7726129173122893,
                    3.0705059731575934,
                    3.18241707888258,
                    3.484888540487614,
                    4.244582678539595,
                    5.177145947610806,
                    5.229822282208742,
                    5.914105277472035,
                    8.099609268268757,
                    9.293383862434988,
                    12.070635125120903,
                    13.009160024649871,
                    13.05368671213009,
                    13.863782727040505,
                    14.414999763296038,
                    14.724470496469639,
                    15.86738167271089,
                    15.871420575852511,
                    17.13039295351508,
                    17.52856672019609,
                    17.935150511498115,
                    18.213677313914403,
                    19.10653920204188,
                    19.280540900623436,
                    19.37107384918069,
                    19.82773173678131
                ],
                "theta": [
                    0.07783381792931737,
                    0.08413122064775813,
                    0.09635676063421156,
                    0.009682528814054204,
                    0.0671145907886225,
                    0.0807110854425443,
                    0.030354841674915558,
                    0.09677884957068245,
                    0.03188723868765223,
                    0.014239977257417137,
                    0.062430536261883024,
                    0.08390136904883867,
                    0.06683104159583277,
                    0.03266890526212314,
                    0.025031584987035574,
                    0.026391603058369007,
                    0.07380071038112486,
                    0.025754937505838228,
                    0.068029857782785,
                    0.0656325500428048,
                    0.010601561004452243,
                    0.03917292645376801,
                    0.07076854620025086,
                    0.0026242841764679394,
                    0.08410010102056337,
                    0.07716801657541117,
                    0.04283355094683462,
                    0.07288351507390772,
                    0.07420406025364626,
                    0.07224391188489246,
                    0.07177586162643483,
                    0.01872720849016163,
                    0.06319658104295056,
                    0.09069012012169958,
                    0.032897183039832294,
                    0.05446660963438171,
                    0.0073622558517991606,
                    0.0794635806172011,
                    0.039201356064271255,
                    0.030432506293733744,
                    0.012804897634780078,
                    0.037685828010674306,
                    0.01469985903372778,
                    0.007236171293828076,
                    0.07814267166162671,
                    0.04857011743960543,
                    0.0091828638574879,
                    0.04535613763355365,
                    0.029021924625591024,
                    0.073829671018724,
                    0.09941689689096957,
                    0.028852896393544637,
                    0.05461030501559086,
                    0.008112149005922586,
                    0.09573252280333612,
                    0.08408362585842029,
                    0.02289500165131847,
                    0.09369678375256421,
                    0.07606425172452354,
                    0.03922047974799379
                ]
            },
            {
                "time": [
                    0.5154812742937964,
                    1.4369677863373598,
                    1.9502845191950335,
                    3.4561493215934536,
                    5.257180137246859,
                    5.554608911485463,
                    5.7464652564080225,
                    9.667012662233276,
                    9.708420279178709,
                    11.173852787756172,
                    11.26367954861999,
                    11.574458842564363,
                    13.0659851428116,
                    13.594943269095998,
                    13.73198938694696,
                    14.12664111937364,
                    14.410679865267497,
                    15.025404535068043,
                    15.044600706891345,
                    15.088950581084204,
                    15.42613969437787,
                    15.517655515416052,
                    16.77668636836387,
                    16.87640770683713,
                    17.04996227239685,
                    17.182380059591715,
                    17.326038166111868,
                    17.482535935895683,
                    18.83719016029717,
                    19.916514673533193
                ],
                "theta": [
                    0.06383792690588763,
                    0.09337079738050967,
                    0.09309009878651515,
                    0.026579685844475766,
                    0.03557838852356942,
                    0.0717629069431884,
                    0.007931427859211294,
                    0.003393437078893169,
                    0.08337327824205604,
                    0.07124187385705202,
                    0.032785840893503136,
                    0.0982439914435265,
                    0.004258930721532073,
                    0.06680900087656157,
                    0.07377724002692222,
                    0.04252624021180893,
                    0.04351229526077153,
                    0.008769002699793227,
                    0.09790756840704248,
                    0.08183448019939074,
                    0.048742571442260275,
                    0.049193218105706406,
                    0.08034701235695371,
                    0.051807033866981905,
                    0.09802865917970278,
                    0.07983669712321893,
                    0.09216249189094872,
                    0.09808704614053086,
                    0.04530114904330493,
                    0.014596557645407427,
                    0.020485240811995653,
                    0.01391871424130281,
                    0.07674625342394892,
                    0.027791249388694463,
                    0.04001270782042097,
                    0.010782066883694652,
                    0.009054277876695271,
                    0.014742810517676641,
                    0.024507977016114093,
                    0.043874707513727795,
                    0.025893831107411336,
                    0.019375233747285593,
                    0.07878178709021826,
                    0.01204599848280229,
                    0.0297617091509919,
                    0.002323279278902579,
                    0.08236689483644953,
                    0.047362624849685724,
                    0.08638892874599549,
                    0.011796440541083565,
                    0.01885045267874047,
                    0.035581076711217456,
                    0.08181784555606068,
                    0.0790881265552469,
                    0.08712525677880803,
                    0.07381547037725869,
                    0.025935652611554352,
                    0.055644896940431426,
                    0.032625517811383585,
                    0.04790826858223321
                ]
            },
            {
                "time": [
                    1.1669509398582645,
                    1.4075048473920648,
                    1.6014158969638603,
                    2.0808835265216574,
                    2.3635219736841995,
                    3.128236384751477,
                    3.295114485035846,
                    3.5695534068354973,
                    4.382758839777083,
                    7.314059663138492,
                    7.405426029261304,
                    8.030878767946232,
                    8.634157999626881,
                    9.394849199945002,
                    10.487092705235735,
                    10.497265465147956,
                    12.43077919534144,
                    12.467097014836245,
                    12.730062208328668,
                    12.884904414618951,
                    13.087760403363593,
                    13.174102440394558,
                    13.436248864040575,
                    14.700026059469703,
                    14.794836779936023,
                    15.667427172469244,
                    16.057682443298933,
                    16.92566692476119,
                    17.255381186299545,
                    18.17895846256378
                ],
                "theta": [
                    0.07143028221793524,
                    0.058591029472448854,
                    0.07134531399659565,
                    0.03175556452095909,
                    0.06049091202947407,
                    0.034181933909557795,
                    0.07916779776672223,
                    0.06207470089852263,
                    0.018625813068972288,
                    0.010174119277815342,
                    0.02045357619383689,
                    0.00968023391037628,
                    0.03749190021297632,
                    0.059019327454883586,
                    0.02397464844054048,
                    0.09691336887718201,
                    0.0025608385456155737,
                    0.05237420143491566,
                    0.043796967631346675,
                    0.025635157626237116,
                    0.04319097803809942,
                    0.04153466151867539,
                    0.08034381773745308,
                    0.028587452341732246,
                    0.016800065747580528,
                    0.0053962434999864865,
                    0.05799272749508652,
                    0.051413693201074896,
                    0.08342505443327378,
                    0.02076368614737958,
                    0.014388391367423647,
                    0.09674477254518363,
                    0.04088816733020298,
                    0.06523079756100912,
                    0.05836836832890491,
                    0.06855249979428063,
                    0.09396271872120214,
                    0.018413978348758877,
                    0.03780035290745912,
                    0.03247407188221566,
                    0.03659294387371194,
                    0.09157646006237763,
                    0.036974969049569706,
                    0.0540875623920742,
                    0.017507956918853197,
                    0.06469256867520355,
                    0.09246454317906269,
                    0.011766876752975865,
                    0.06137977337621673,
                    0.07789066076295434,
                    0.014948705245110251,
                    0.001464874593514054,
                    0.08570471665707552,
                    0.011219615185508215,
                    0.04205108744452614,
                    0.009324101965839637,
                    0.04637736679643287,
                    0.009951098828215566,
                    0.019969050104085086,
                    0.03063209554753278
                ]
            }
        ],
        "optimized_minimum_cost": [
            -6.023543338103273,
            -6.013617709006477,
            -6.022456943015584,
            -6.025345930326605,
            -6.025102390268693,
            -6.011626862385263,
            -6.025292557030687,
            -6.018923399002861,
            -6.024519906256709,
            -6.025159340170406
        ],
        "optimized_parameters": [
            [
                0.44206980160257614,
                0.44206980160257614,
                1.6679305296797082,
                1.9078041086552968,
                1.9078041086552968,
                3.937047545451033,
                5.208465008361973,
                5.388300705412353,
                6.149193012182072,
                7.572942296238934,
                8.563998725364394,
                8.563998725364394,
                8.920531610584854,
                9.602255467218958,
                11.001250172101043,
                11.767038966084204,
                11.776612002272689,
                11.966141161345213,
                13.03467653996121,
                13.058277236441793,
                13.058277236441793,
                13.058277236441793,
                14.395254950325782,
                15.217829372106362,
                16.94369644407038,
                17.071533969836395,
                18.382907243391514,
                18.382907243391518,
                19.522434625256377,
                20.0,
                20.698762101352116,
                -0.1272257824997467,
                0.5235793711037457,
                0.31688616161111194,
                -1.8832166009941302,
                1.3027462704474304,
                0.6036256768042202,
                -0.5169909405685946,
                1.6017285873701377,
                -0.6501856289796891,
                1.400788604043119,
                -0.28412371878499765,
                1.4098723121993793,
                0.3201068261018203,
                2.2557774786624796,
                0.6233675297240749,
                1.1161306266597737,
                0.1366894652172077,
                1.5490039304181853,
                0.5138178262876402,
                1.246934969255791,
                -0.5514435986859991,
                1.6480641354732044,
                -0.37090640793546037,
                0.8381241413097886,
                -0.37565311808894597,
                0.20292840340466042,
                1.4378164089684595,
                0.17701554143224496,
                0.23991453724056291,
                0.44326436760519855,
                -0.7657060688274102,
                0.9679005091128426,
                -1.181082008011901,
                -0.40530119884347005,
                -0.3693631276195587,
                -0.04466527627014401,
                0.3328935705168993,
                1.055993033215117,
                0.41975651556193405,
                0.7901962049741905,
                0.12564875276299659,
                0.3233813560245452,
                -0.19552634132631477,
                1.6354782990983217,
                -0.5299635284688524,
                0.7588259332518306,
                -0.056172300059902175,
                -0.6882068568152928,
                -1.45707555100624,
                1.2465223697610248,
                -0.5218827197033531,
                1.3214013716953976,
                0.04324628466159724,
                1.2146658137678825,
                0.6194156615099192,
                1.5767763497169565,
                1.0161183246727636,
                -0.6265238764936004,
                1.3024993839638377,
                0.06645928238216513
            ],
            [
                1.6115275391718509,
                2.5877040076302786,
                2.5877040076302786,
                2.769133102023885,
                4.680930128494912,
                4.741602637962305,
                5.98147524759552,
                5.98147524759552,
                7.474895473192188,
                7.474895473192188,
                8.940178428722632,
                10.342898242307156,
                11.058037823719173,
                12.843438131912157,
                12.843438131912157,
                13.860347847390557,
                13.889525821363845,
                14.911812422378983,
                14.911812422378983,
                14.94972161610309,
                15.42372099285765,
                15.42372099285765,
                15.620067416814939,
                16.54239218079748,
                16.54239218079748,
                16.54239218079748,
                17.79941587029069,
                17.79941587029069,
                19.25572686661144,
                20.0,
                21.56846627432257,
                -0.2590355590852755,
                -0.1498643975887078,
                0.38878721606392513,
                -0.3588426744052543,
                1.1797826967848966,
                0.9853064181092797,
                1.2870854914079128,
                1.3200240466563242,
                1.3568930545114548,
                1.4219678980233665,
                -0.7260210943292301,
                0.23887288851730862,
                -0.2946719417134541,
                1.7974657065317532,
                0.3185064855279575,
                0.035041060689668974,
                0.6755064086382464,
                1.9802090710600564,
                1.0700441854604057,
                1.263663664234374,
                0.40390986548982727,
                1.083735169247879,
                -1.5503758046756746,
                2.552494767537011,
                1.1038003018797606,
                1.9335014655256204,
                -1.9547782521042631,
                1.2707508321569168,
                -1.330188172935359,
                1.114455726773572,
                -1.9654736717629673,
                0.4273168862028301,
                0.6608470889387502,
                0.547464070274314,
                1.4893460038343078,
                1.0279840710612616,
                0.9859110059855342,
                1.3235394898079362,
                0.7508928709110084,
                0.24984123479697046,
                0.9054124690838062,
                -1.6461714019130407,
                0.11776647507644752,
                -1.0090775745603284,
                0.6732002825743887,
                -1.0707455076225827,
                -0.7519312851350142,
                0.5289432096058936,
                -0.9473237016702806,
                0.7759438143037221,
                -1.5092501128116464,
                0.642733210387321,
                -1.1608215802479678,
                1.1945130574016618,
                -0.33090047038016696,
                1.0963502413141266,
                1.7135485534429407,
                1.0451805610231288,
                1.6971820337903476,
                0.04175654022463731
            ],
            [
                0.48856230984197296,
                0.48856230984197296,
                1.1045153361031899,
                1.1045153361031899,
                1.7063525333615235,
                1.7816739396819887,
                2.1872769929845326,
                2.3771507272466432,
                2.8367150697187213,
                2.8469192688956517,
                3.18389463840537,
                3.1853060889925646,
                3.8366235655496346,
                4.790581631130009,
                5.608058770571685,
                5.916290361636256,
                7.592061507903915,
                8.01729852456039,
                8.370473951485636,
                9.285332492012788,
                10.494147874090697,
                11.658092190873884,
                11.658092190873884,
                12.838338102351727,
                14.885347687210663,
                16.275170776802213,
                18.511190948341252,
                19.240494884866767,
                19.983522550700435,
                20.0,
                22.228943640912835,
                -1.3583296548342223,
                0.27473808464878413,
                1.5446166483704329,
                1.1980352721667746,
                0.5985435577545489,
                1.0046326232263971,
                2.0539496437378144,
                -0.19391701099537842,
                0.853944375452408,
                0.7283875197780627,
                0.4989616500368467,
                0.23466098100117846,
                0.714021071202879,
                1.0012226033075602,
                0.9799962684352779,
                0.7629646970439383,
                0.810335956116671,
                1.38183867432108,
                -0.26498414069781967,
                1.3221486927379618,
                -0.11744058569125572,
                0.9319258016202263,
                -0.12169699634091843,
                0.6798732729190546,
                1.4991065465693985,
                1.4131016147159585,
                -0.2883735045550925,
                0.5530366889376163,
                1.0701754147551057,
                1.6244511317265706,
                1.4082355266586521,
                -0.2037258933517442,
                -0.03864271970708052,
                1.6144058328685043,
                1.4223786855519556,
                -0.5591830823177038,
                0.4986503340040518,
                2.811623478314936,
                -0.2313371486755112,
                1.7545014276265838,
                1.7112381033173738,
                0.8717043684660257,
                -2.8306672594208515,
                2.531085258097232,
                0.48010460182490544,
                0.08539707680452782,
                -0.6204853879276455,
                0.9956943148610365,
                -0.6901161151860676,
                1.3367529677930605,
                -0.394168682777467,
                1.5110001344878938,
                -0.044330113820078364,
                0.934674331386092,
                -1.290857861372358,
                0.40317096443879263,
                -0.6809789399797703,
                1.1987890718223295,
                1.816556765496996,
                0.04014671941232992
            ],
            [
                0.38078834677603013,
                0.6328431979071237,
                0.9187932618422264,
                1.4940103432250738,
                1.8694437186379307,
                2.3632916494260576,
                2.3782463216058227,
                2.9620378660066753,
                3.0225819131663765,
                3.5577745491516266,
                3.9492235063028693,
                4.380200228220079,
                4.419472927261504,
                5.138753641237604,
                5.593795253647293,
                6.3740712060846905,
                8.169798903046907,
                9.62276669819157,
                10.439694699659986,
                11.001765481936202,
                11.140876607986689,
                12.194982876346026,
                13.0183340470349,
                14.938458721463263,
                15.833058701932071,
                15.833058701932071,
                16.319428616925705,
                17.810703080055085,
                18.984023448182576,
                20.0,
                20.911712194583828,
                0.2696234145295062,
                0.9826583881635309,
                1.891009325646793,
                0.40940446282042314,
                1.7520858569316593,
                1.0593202240004833,
                0.21708756802738916,
                0.9090370649351068,
                -1.358057761872928,
                1.5857092937610584,
                -0.7109154408648596,
                2.564091282302896,
                -0.0193054390124427,
                0.5717267626445303,
                0.905487467593346,
                1.195807056583011,
                0.4758308956701482,
                1.2309320884191095,
                0.32332534115083555,
                1.7057400295322134,
                1.62995563679887,
                1.5764848367492184,
                -0.0491827145928259,
                0.9932520415822743,
                1.5545618490414332,
                1.5831403308406449,
                -0.07945191623964935,
                0.7676104504669452,
                2.198094722064117,
                0.6459316601420589,
                0.9946271132844781,
                2.350271690651623,
                0.8041488950096071,
                1.680239736587364,
                1.0793352636730262,
                0.8209557600119116,
                0.6208053576226531,
                0.719573485862218,
                -0.12619376042171176,
                0.5268746772692382,
                -0.42583238547089386,
                0.4003308298224003,
                -0.08961687757446342,
                1.2588101305283856,
                -0.04199191094271479,
                1.0788442620213459,
                0.8376612644016015,
                0.16510619594963252,
                1.4566514617802053,
                1.1163794996578675,
                0.8715647153270843,
                -0.07382666529026768,
                -1.4246152442318767,
                1.1711083135252338,
                -1.0554082066034116,
                0.9376044226708242,
                -0.4883680516827095,
                1.309623124488176,
                -0.030554676611319897,
                0.04469540726160305
            ],
            [
                0.28665839949178834,
                0.3432317200153415,
                1.5941505877411253,
                1.5941505877411253,
                1.5941505877411253,
                3.3558773989419652,
                5.0205469005320005,
                6.056266128381812,
                6.353673581047162,
                7.958132310528882,
                7.9654808802789265,
                8.56394932836063,
                9.195728133243456,
                9.293296959977638,
                10.422428784731306,
                11.286804540504765,
                11.28982459110164,
                12.769388695768253,
                13.031009528816934,
                13.234906540577116,
                14.710531580795639,
                14.940899095579343,
                14.940899095579343,
                15.649784086753533,
                16.36903565243179,
                16.52474350851688,
                17.929772067413733,
                19.13753370373444,
                19.449088439232305,
                20.0,
                21.27430201493362,
                0.9555135467763923,
                1.1814996734164387,
                -2.0370627849936414,
                0.297756393933971,
                0.5311725555302752,
                0.454824424697578,
                0.2425328003389815,
                0.6756711951793344,
                0.31316676789431314,
                0.9434038450364427,
                0.9422938204993166,
                0.9768591507568034,
                0.7448051488742148,
                0.5928365568965246,
                1.3508540003109828,
                -0.5543079684099335,
                0.17998329828102172,
                -0.20303915947658743,
                -1.7412770155175645,
                -0.8940172051435943,
                -1.2143630993404377,
                0.4639358993367856,
                -1.1528598588226229,
                1.2726827628038633,
                -0.5480061909470959,
                1.276173980403206,
                0.7686994481748428,
                0.6964181262462067,
                0.36614940458329726,
                0.4691531786581758,
                -2.1830615231128996,
                1.3324595202409097,
                -0.76110476251455,
                0.6639321956660229,
                -1.191915565832348,
                0.8526212695258781,
                -0.6716799385819134,
                0.9374731544324734,
                0.6267903922070771,
                1.3487815458057575,
                0.47134400328844733,
                0.9775407744847588,
                -0.7099595622247087,
                1.3826490155247377,
                1.4924491293040645,
                0.3031106559204129,
                0.35788556701454655,
                0.8422516772686295,
                1.615008359216392,
                1.7451518581291503,
                -0.934435248002859,
                1.878730732979285,
                0.662527997526751,
                2.5575869287792026,
                0.364394054071107,
                1.6133730184797412,
                0.4484332999397296,
                0.7262161812630165,
                0.8400652982013798,
                0.07098216238512765
            ],
            [
                0.7950833985187138,
                1.2419507312403122,
                2.4097570552769803,
                2.8184018658696504,
                3.730280865101926,
                3.741386915819601,
                3.741386915819601,
                4.408086943764009,
                4.578062985443201,
                4.968851712269042,
                4.968851712269042,
                4.968851712269042,
                5.876774890253377,
                9.579593831266564,
                9.584552613337795,
                10.168657752734957,
                10.351137030331472,
                11.313534847764856,
                12.608543500173786,
                13.953101184891944,
                14.17480080614987,
                14.49793193816053,
                15.149902611162313,
                15.825371855281787,
                16.618402539560762,
                16.618402539560762,
                17.891384549462973,
                18.12172503190428,
                18.873943216739498,
                20.0,
                19.268050050528426,
                -1.5662140343272843,
                -0.20960800181516376,
                0.47304493623343885,
                1.976755452888605,
                0.25631404158608856,
                -0.6337210284053385,
                0.6556845896468221,
                -0.8284189666497476,
                -0.7762149791565227,
                1.126761395998041,
                -0.931389647876806,
                1.609977069176532,
                -0.32228574309702096,
                -0.2986641565349988,
                0.3881880433503495,
                -1.0163052434110382,
                0.5568824173899967,
                1.4976737913371054,
                1.144087081027601,
                0.6922090295561732,
                2.0992976057523522,
                -0.4994263155542168,
                1.737248825419122,
                1.2748445075049977,
                2.7782613996874295,
                -0.5115292580350995,
                -3.014224324518117,
                1.870422722591855,
                0.2030068258032883,
                0.2635161575641149,
                0.4444384634767166,
                0.09155929893949584,
                0.0014349093495717854,
                1.2347020992019495,
                -0.1849600152485983,
                0.24381101367701738,
                -1.894374412539302,
                1.06252101616564,
                -2.2485114658563803,
                1.9669531186243634,
                0.2074981742578064,
                2.321407653418984,
                0.31234872048457846,
                -1.2529010661350637,
                0.010105394159425355,
                0.44241924689976136,
                -3.8570437687167765,
                -0.20726091548190478,
                -0.8742074920641899,
                1.0486799930883248,
                0.5484277640105262,
                0.8023314268726414,
                -1.547940939279492,
                1.5299254398288924,
                -0.9959499592949206,
                0.16889358107794603,
                1.7350696582714586,
                2.2480894294404115,
                -0.9644283369436677,
                0.07768984571627603
            ],
            [
                0.6143097503860863,
                0.6143097503860862,
                0.8841050146515564,
                0.9614247416083764,
                3.1368496898266773,
                3.211080622513643,
                3.4702938246530985,
                5.0341158667322174,
                5.352774658068103,
                5.401457896343629,
                5.584428315684204,
                6.796496542335845,
                6.796496542335845,
                7.218457898587052,
                8.10167966615576,
                8.95775157674153,
                9.8849315659826,
                12.858987210355089,
                12.927018136324618,
                14.690567959878354,
                15.461235279272982,
                16.234361662566894,
                16.234361662566894,
                16.725853434504142,
                16.945930680529983,
                17.72778859098624,
                18.36837831982395,
                19.053930595094464,
                19.7137532197345,
                20.0,
                21.036850707141763,
                0.03116114510403902,
                1.8336240951767855,
                -0.2810063986769598,
                1.249744095293241,
                -0.168038786420218,
                0.9576013203102912,
                0.10280246751764384,
                -0.08656446161645166,
                0.809320691292899,
                -0.040376110304759114,
                0.68676144850805,
                0.35585837719927543,
                0.3388235532000334,
                0.30380010548622194,
                -0.7431463387645137,
                0.531265809371977,
                1.5642780613481033,
                -0.21446223536953354,
                2.2244405766959954,
                -0.4632925803677591,
                -0.5445082921413421,
                0.690023256546485,
                0.740611331235425,
                0.5176163263701247,
                0.6670548429494786,
                1.166284835033596,
                0.7652389241976495,
                1.6357381194480087,
                0.14107510198954534,
                1.2462600503029706,
                -0.9681309212473835,
                0.49581934204165024,
                1.918471153777945,
                0.2221891413625717,
                -1.443144779296965,
                2.0261753416833197,
                -0.39948204198389814,
                -0.08303469107458938,
                0.6225288340095175,
                0.19194541273784305,
                -0.1696818987217068,
                -1.1519762273557987,
                0.2961309712644359,
                -0.32205377047104816,
                -0.8117108847467561,
                1.7332482096505926,
                0.35643245396731243,
                1.478431071800201,
                0.8398989885153859,
                0.45094206397721337,
                1.5968004861789489,
                1.5785664586981765,
                0.834910561818929,
                0.7405523884771914,
                -0.11906880733381518,
                0.8198685559338037,
                2.411859681182571,
                2.1586953118241796,
                0.027732684129407034,
                0.09029033908596124
            ],
            [
                -1.2748589754653087e-17,
                0.6629189690133307,
                0.6629189690133307,
                1.5385263241679508,
                1.5385263241679508,
                3.2554490645332805,
                3.966361429542776,
                4.127117115695168,
                4.414522474210218,
                4.843924442982488,
                5.1789830013115425,
                6.548141276117095,
                7.7763311845116565,
                8.91818009963059,
                12.0375629976573,
                12.0375629976573,
                12.0659850629694,
                13.785885009892173,
                14.27264454175125,
                15.02759942705866,
                15.02759942705866,
                16.029851521233553,
                16.856053984225856,
                17.15084489530929,
                17.983480677979664,
                18.242727907592553,
                18.242727907592553,
                18.242727907592553,
                18.86017431679795,
                20.0,
                21.353676284214306,
                -0.40148349144957807,
                0.5932087999455999,
                0.5012543014139641,
                0.3561045551323839,
                0.21115682469452252,
                0.3557045274089096,
                0.7398357668844017,
                0.12489999413042677,
                1.2032271701517132,
                -0.4561958395818797,
                1.074232525555147,
                -0.24555395346401518,
                1.2889177384036392,
                1.115425744258021,
                -0.19566543204320586,
                2.0034406398081206,
                -1.6402928701654371,
                -0.3231669766731418,
                1.362476267468206,
                0.4495094902699735,
                0.7448555720991739,
                -0.5659782283717224,
                0.9000489641857212,
                1.4561028641192513,
                1.2762840446004176,
                2.298991319730591,
                1.7919359456945883,
                0.47364185580206825,
                -2.463810594873355,
                0.4518938375360238,
                -0.8480543721830804,
                1.1135775276094806,
                -0.3668654671343982,
                0.1398462134278474,
                -1.0326114221041611,
                1.4282640821336445,
                -0.8987362593555978,
                0.5871178565603863,
                0.9774994376005264,
                1.2807528236529657,
                -0.7526238666125818,
                1.406753341446309,
                0.0947829028185166,
                0.869376918719638,
                -0.6945919660371931,
                2.733891869230875,
                -1.0096747096763792,
                1.3427009877020846,
                2.1753821771379505,
                0.6010690681287907,
                1.1539409057707715,
                1.1682998071223045,
                2.098590807519599,
                1.490169524806628,
                1.5316752491327652,
                2.1949290061479827,
                1.3538174633979787,
                0.22336645092207888,
                2.3055769181153334,
                0.03922047974799379
            ],
            [
                0.6093762678107552,
                0.9737138372480537,
                3.5125822265876363,
                3.8395694109720075,
                5.493630086994667,
                5.713015647373265,
                6.036171756780131,
                8.969701469411184,
                9.302082141228409,
                10.214000366712167,
                10.83177852551854,
                11.959792707593747,
                12.676000325838059,
                13.03671411493636,
                13.03671411493636,
                13.40597902836623,
                14.834947940579806,
                14.834947940579806,
                14.834947940579806,
                14.834947940579806,
                15.617891930626438,
                15.654046683330597,
                16.517201240683796,
                16.83005421188913,
                16.866702229237255,
                16.866702229237255,
                16.950334534216395,
                17.649648838510778,
                18.578047273430805,
                20.0,
                21.59227551864538,
                1.353212666226694,
                1.5664801290386996,
                -0.5062986117904738,
                0.5094822070454218,
                2.001337619326328,
                1.8963450719600803,
                -1.761006201672981,
                1.468700313354738,
                -0.35515897589338774,
                0.4899405269514627,
                -0.1788015993440183,
                2.1434782932988474,
                0.7509796416827832,
                1.0554232062787445,
                -0.4838573001890244,
                1.406599543873984,
                -1.3411051487058483,
                -0.24807140459972948,
                1.3945330642883118,
                1.817862044922444,
                1.5274818368145016,
                0.013060232161869164,
                1.3997054435876437,
                1.4399189366944405,
                -1.0970674195064662,
                0.1920676505855223,
                1.5983935334215948,
                0.9354576404284438,
                0.1147496334123365,
                1.0191913672648603,
                1.0026749642289428,
                0.006910540179026223,
                -0.37393168421577033,
                1.3224172137253778,
                0.10264450206689778,
                1.716651651721245,
                0.06490968913013943,
                1.4991355493062588,
                0.13826045879584212,
                0.3364543511232694,
                0.8169492890152442,
                0.531744162616839,
                1.3674351902073791,
                -0.12544002824275613,
                0.5637100914577983,
                0.8019405097455505,
                -0.20034665134593427,
                1.1007637757652393,
                -0.6725307710138363,
                0.6861503297907026,
                -0.683274761054823,
                0.6312696285205145,
                -0.0027500708128624547,
                0.9099442341645476,
                -1.1663048534224283,
                1.8048510660458588,
                0.3284902079969842,
                1.4194783426521305,
                0.2532703425420499,
                0.04790826858223321
            ],
            [
                0.7592957384960186,
                1.1748758386673135,
                1.5531633228903503,
                2.2632009408878377,
                3.2232349699799854,
                3.491946459864995,
                3.7529217324255773,
                3.7717148343270925,
                3.7723063827378516,
                6.830704740551258,
                6.867291342265259,
                8.350618142285915,
                9.231256428425676,
                9.732513355733314,
                10.497762511730096,
                10.606281370995621,
                11.518401804101607,
                11.518401804101607,
                11.731766583392657,
                12.881419898110897,
                12.881419898110897,
                12.881419898110897,
                12.881419898110897,
                14.260475484981317,
                15.19321751838948,
                15.196297654148582,
                15.614211677563448,
                17.758988411574943,
                17.758988411574943,
                20.0,
                20.136733479983782,
                1.5400303389979988,
                -0.4715811490028105,
                0.6678261039937794,
                0.8655677365558656,
                -0.14604891309982101,
                0.17135611230425035,
                1.3396027362274399,
                0.6467134179793026,
                1.1124067089483285,
                0.8682270158827964,
                0.3258062445020569,
                0.3243698770303807,
                -0.6801789649714763,
                1.0325088756441079,
                -0.5596894015237547,
                1.1573884748726526,
                0.4341910446410259,
                1.7968552940471405,
                -0.22491079990905552,
                1.623368687384146,
                -0.8144365658292055,
                -0.5552063633228324,
                0.9989636084361093,
                1.261258846021703,
                1.346799585546086,
                0.8862276763859281,
                -0.6671289245057801,
                0.5655773606728944,
                1.9825248584879211,
                1.0668916201350198,
                -1.0117613213465557,
                0.2941706845669399,
                -1.0960721986044903,
                2.496482943538803,
                0.9964559472910854,
                0.746068134068851,
                -1.438430773802844,
                0.3162844116054356,
                0.21698768329354826,
                0.487021707673603,
                2.1189840482450147e-05,
                0.5809142071673461,
                -0.1847438816407459,
                0.660285463551747,
                -0.22815171174102258,
                1.3394129836250985,
                0.3529967234876451,
                1.2674523489528746,
                0.8018111599301461,
                1.0429870945330653,
                -0.4411446434655921,
                -0.9466127022212372,
                -0.5826500568560149,
                0.46667848585253946,
                -1.045548247742723,
                2.1915019538219336,
                0.7194517708338989,
                0.2341659208207253,
                1.4699282653750767,
                0.03063209554753278
            ]
        ],
        "noise_details": {
            "identity_factors": [
                0,
                0,
                0,
                0
            ],
            "noise_level": [
                0,
                0,
                0,
                0
            ],
            "gates_num": [
                4,
                1,
                1,
                0
            ],
            "noise_profile": {
                "status": false,
                "type": "dephasing",
                "noise_prob": [
                    0.001,
                    0.001,
                    0.0,
                    0.0
                ],
                "noise_on_init_param": {
                    "status": false,
                    "value": 0
                }
            },
            "odd_wires": 3
        },
        "run_time_sec": 452.3842623233795
    },
    "others": {
        "observable_string": "1 X 0 X 1 + 1 Z 0 + 1 X 1 X 2 + 1 Z 1 + 1 X 2 X 3 + 1 Z 2 + 1 X 3 X 4 + 1 Z 3 + 1 Z 4",
        "time_evolution_gate_hamiltonian_string": [
            "0.5 X 0 X 1 + 0.5 Y 0 Y 1 + 0.5 Z 0 Z 1 + 0.5 X 1 X 2 + 0.5 Y 1 Y 2 + 0.5 Z 1 Z 2 + 0.5 X 2 X 3 + 0.5 Y 2 Y 3 + 0.5 Z 2 Z 3 + 0.5 X 3 X 4 + 0.5 Y 3 Y 4 + 0.5 Z 3 Z 4"
        ]
    }
}